dcentralab_auto_infra/__init__.py
dcentralab_auto_infra-1.5.0.dist-info/LICENSE
dcentralab_auto_infra-1.5.0.dist-info/METADATA
dcentralab_auto_infra-1.5.0.dist-info/WHEEL
dcentralab_auto_infra-1.5.0.dist-info/top_level.txt
dcentralab_auto_infra-1.5.0.dist-info/RECORD
